ce_forms/__init__.py
ce_forms/client.py
ce_forms/accounts/__init__.py
ce_forms/accounts/accounts.py
ce_forms/api/__init__.py
ce_forms/api/bearer_auth.py
ce_forms/api/client.py
ce_forms/api/exceptions.py
ce_forms/api/modules.py
ce_forms/assets/__init__.py
ce_forms/assets/assets.py
ce_forms/form/__init__.py
ce_forms/form/form.py
ce_forms/processing/__init__.py
ce_forms/processing/processing.py
ce_forms/processing/task.py
ce_forms/processing/task_pool.py
ce_forms/query/__init__.py
ce_forms/query/form_mutate.py
ce_forms/query/forms_query.py
ce_forms/query/forms_res.py
ce_forms-0.0.5.dist-info/LICENSE
ce_forms-0.0.5.dist-info/METADATA
ce_forms-0.0.5.dist-info/WHEEL
ce_forms-0.0.5.dist-info/top_level.txt
ce_forms-0.0.5.dist-info/RECORD
